{
  "cities": [
    {
      "cityName": "Lisbon",
      "country": "Portugal",
      "emoji": "🇵🇹",
      "date": "2027-10-31T15:59:59.138Z",
      "notes": "My favorite city so far!",
      "position": {
        "lat": 38.727881642324164,
        "lng": -9.140900099907554
      },
      "id": "73930385"
    },
    {
      "id": "1cf7",
      "cityName": "Palacios del Arzobispo",
      "country": "Spain",
      "emoji": "🇪🇸",
      "date": "2025-11-27T09:30:34.131Z",
      "notes": "wfhalhs",
      "position": {
        "lat": "41.178653972331674",
        "lng": "-5.888671875"
      }
    },
    {
      "id": "23fe",
      "cityName": "Hervas",
      "country": "Spain",
      "emoji": "🇪🇸",
      "date": "2025-11-27T09:30:42.193Z",
      "notes": "wlafhlF",
      "position": {
        "lat": "40.27952566881291",
        "lng": "-5.800781250000001"
      }
    },
    {
      "id": "3b52",
      "cityName": "Campo de Criptana",
      "country": "Spain",
      "emoji": "🇪🇸",
      "date": "2025-11-27T09:30:48.320Z",
      "notes": "slfhalhfs",
      "position": {
        "lat": "39.436192999314095",
        "lng": "-3.0541992187500004"
      }
    }
  ]
}